treely/__init__.py
treely/main.py
treely-1.1.1.dist-info/METADATA
treely-1.1.1.dist-info/WHEEL
treely-1.1.1.dist-info/entry_points.txt
treely-1.1.1.dist-info/licenses/LICENSE
treely-1.1.1.dist-info/RECORD
