Metadata-Version: 2.4
Name: treely
Version: 1.1.1
Summary: A modern, beautiful and powerful command-line directory tree generator with advanced filtering and code-viewing capabilities.
Project-URL: Homepage, https://github.com/rudra-mondal/treely
Author-email: Rudra Mondal <rudramondal815@gmail.com>
License: MIT License
License-File: LICENSE
Keywords: cli,directory,dirtree,foldertree,generator,structure,tool,tree,treegen,treely
Classifier: Environment :: Console
Classifier: License :: OSI Approved :: MIT License
Classifier: Operating System :: OS Independent
Classifier: Programming Language :: Python :: 3
Classifier: Topic :: System :: Filesystems
Requires-Python: >=3.7
Requires-Dist: pathspec>=0.12.1
Requires-Dist: pyperclip>=1.8.2
